webassets_elm.py
webassets_elm-0.2.1.dist-info/LICENSE
webassets_elm-0.2.1.dist-info/METADATA
webassets_elm-0.2.1.dist-info/WHEEL
webassets_elm-0.2.1.dist-info/top_level.txt
webassets_elm-0.2.1.dist-info/RECORD
