Metadata-Version: 2.1
Name: webassets-elm
Version: 0.2.1
Summary: Elm filter for webassets
Home-page: https://github.com/cuducos/webassets-elm
Author: Eduardo Cuducos
Author-email: cuducos@gmail.com
License: MIT
Keywords: elm,webassets,assets,django,flask
Platform: UNKNOWN
Classifier: Development Status :: 4 - Beta
Classifier: Environment :: Web Environment
Classifier: Framework :: Django
Classifier: Framework :: Flask
Classifier: Intended Audience :: Developers
Classifier: License :: OSI Approved :: MIT License
Classifier: Programming Language :: Python :: 3.5
Classifier: Programming Language :: Python :: 3.6
Classifier: Programming Language :: Python :: 3.7
Requires-Python: >=3.5
Requires-Dist: webassets
